obiscr_django_ratelimit/__init__.py
obiscr_django_ratelimit/apps.py
obiscr_django_ratelimit/checks.py
obiscr_django_ratelimit/core.py
obiscr_django_ratelimit/decorators.py
obiscr_django_ratelimit/exceptions.py
obiscr_django_ratelimit/middleware.py
obiscr_django_ratelimit/models.py
obiscr_django_ratelimit/tests.py
obiscr_django_ratelimit-4.0.7.dist-info/licenses/LICENSE
obiscr_django_ratelimit-4.0.7.dist-info/METADATA
obiscr_django_ratelimit-4.0.7.dist-info/WHEEL
obiscr_django_ratelimit-4.0.7.dist-info/top_level.txt
obiscr_django_ratelimit-4.0.7.dist-info/RECORD
